{
    "$type": "Background",
    "DataName": null,
    "Transparent": false,
    "Smooth": false,
    "Preload": false,
    "Tileset": {
        "VersionNumber": 2,
        "TileWidth": 40,
        "TileHeight": 40,
        "OutputBorderX": 2,
        "OutputBorderY": 2,
        "TileColumns": 7,
        "ItemsPerTileCount": 4,
        "TileCount": 48,
        "ExportedSprite": null,
        "FrameLength": 166666,
        "TileIDs": [
            0,
            0,
            0,
            0,
            1,
            1,
            1,
            1,
            2,
            2,
            2,
            2,
            3,
            3,
            3,
            3,
            4,
            4,
            4,
            4,
            5,
            5,
            5,
            5,
            6,
            6,
            6,
            6,
            7,
            7,
            7,
            7,
            8,
            16,
            24,
            32,
            9,
            17,
            25,
            33,
            10,
            18,
            26,
            34,
            11,
            19,
            27,
            35,
            12,
            20,
            28,
            36,
            13,
            21,
            29,
            37,
            14,
            22,
            30,
            38,
            15,
            23,
            31,
            39,
            16,
            24,
            32,
            8,
            17,
            25,
            33,
            9,
            18,
            26,
            34,
            10,
            19,
            27,
            35,
            11,
            20,
            28,
            36,
            12,
            21,
            29,
            37,
            13,
            22,
            30,
            38,
            14,
            23,
            31,
            39,
            15,
            24,
            32,
            8,
            16,
            25,
            33,
            9,
            17,
            26,
            34,
            10,
            18,
            27,
            35,
            11,
            19,
            28,
            36,
            12,
            20,
            29,
            37,
            13,
            21,
            30,
            38,
            14,
            22,
            31,
            39,
            15,
            23,
            32,
            8,
            16,
            24,
            33,
            9,
            17,
            25,
            34,
            10,
            18,
            26,
            35,
            11,
            19,
            27,
            36,
            12,
            20,
            28,
            37,
            13,
            21,
            29,
            38,
            14,
            22,
            30,
            39,
            15,
            23,
            31,
            40,
            40,
            40,
            40,
            41,
            41,
            41,
            41,
            42,
            42,
            42,
            42,
            43,
            43,
            43,
            43,
            44,
            44,
            44,
            44,
            45,
            45,
            45,
            45,
            46,
            46,
            46,
            46,
            47,
            47,
            47,
            47
        ]
    }
}